[
    {
        "date": "2025-07-06 00:00:00+00:00",
        "temperature_2m": 17.536998748779297
    },
    {
        "date": "2025-07-06 01:00:00+00:00",
        "temperature_2m": 17.687000274658203
    },
    {
        "date": "2025-07-06 02:00:00+00:00",
        "temperature_2m": 16.636999130249023
    },
    {
        "date": "2025-07-06 03:00:00+00:00",
        "temperature_2m": 15.587000846862793
    },
    {
        "date": "2025-07-06 04:00:00+00:00",
        "temperature_2m": 15.487000465393066
    },
    {
        "date": "2025-07-06 05:00:00+00:00",
        "temperature_2m": 15.487000465393066
    },
    {
        "date": "2025-07-06 06:00:00+00:00",
        "temperature_2m": 14.63700008392334
    },
    {
        "date": "2025-07-06 07:00:00+00:00",
        "temperature_2m": 14.78700065612793
    },
    {
        "date": "2025-07-06 08:00:00+00:00",
        "temperature_2m": 14.837000846862793
    },
    {
        "date": "2025-07-06 09:00:00+00:00",
        "temperature_2m": 15.437000274658203
    },
    {
        "date": "2025-07-06 10:00:00+00:00",
        "temperature_2m": 16.536998748779297
    },
    {
        "date": "2025-07-06 11:00:00+00:00",
        "temperature_2m": 17.437000274658203
    },
    {
        "date": "2025-07-06 12:00:00+00:00",
        "temperature_2m": 16.536998748779297
    },
    {
        "date": "2025-07-06 13:00:00+00:00",
        "temperature_2m": 17.73699951171875
    },
    {
        "date": "2025-07-06 14:00:00+00:00",
        "temperature_2m": 17.636999130249023
    },
    {
        "date": "2025-07-06 15:00:00+00:00",
        "temperature_2m": 18.136999130249023
    },
    {
        "date": "2025-07-06 16:00:00+00:00",
        "temperature_2m": 19.437000274658203
    },
    {
        "date": "2025-07-06 17:00:00+00:00",
        "temperature_2m": 20.386999130249023
    },
    {
        "date": "2025-07-06 18:00:00+00:00",
        "temperature_2m": 20.336999893188477
    },
    {
        "date": "2025-07-06 19:00:00+00:00",
        "temperature_2m": 20.437000274658203
    },
    {
        "date": "2025-07-06 20:00:00+00:00",
        "temperature_2m": 19.687000274658203
    },
    {
        "date": "2025-07-06 21:00:00+00:00",
        "temperature_2m": 18.786998748779297
    },
    {
        "date": "2025-07-06 22:00:00+00:00",
        "temperature_2m": 18.187000274658203
    },
    {
        "date": "2025-07-06 23:00:00+00:00",
        "temperature_2m": 17.437000274658203
    },
    {
        "date": "2025-07-07 00:00:00+00:00",
        "temperature_2m": 16.937000274658203
    },
    {
        "date": "2025-07-07 01:00:00+00:00",
        "temperature_2m": 16.386999130249023
    },
    {
        "date": "2025-07-07 02:00:00+00:00",
        "temperature_2m": 16.086999893188477
    },
    {
        "date": "2025-07-07 03:00:00+00:00",
        "temperature_2m": 15.88700008392334
    },
    {
        "date": "2025-07-07 04:00:00+00:00",
        "temperature_2m": 15.737000465393066
    },
    {
        "date": "2025-07-07 05:00:00+00:00",
        "temperature_2m": 15.687000274658203
    },
    {
        "date": "2025-07-07 06:00:00+00:00",
        "temperature_2m": 15.78700065612793
    },
    {
        "date": "2025-07-07 07:00:00+00:00",
        "temperature_2m": 15.78700065612793
    },
    {
        "date": "2025-07-07 08:00:00+00:00",
        "temperature_2m": 15.587000846862793
    },
    {
        "date": "2025-07-07 09:00:00+00:00",
        "temperature_2m": 15.587000846862793
    },
    {
        "date": "2025-07-07 10:00:00+00:00",
        "temperature_2m": 16.036998748779297
    },
    {
        "date": "2025-07-07 11:00:00+00:00",
        "temperature_2m": 16.036998748779297
    },
    {
        "date": "2025-07-07 12:00:00+00:00",
        "temperature_2m": 17.036998748779297
    },
    {
        "date": "2025-07-07 13:00:00+00:00",
        "temperature_2m": 17.336999893188477
    },
    {
        "date": "2025-07-07 14:00:00+00:00",
        "temperature_2m": 17.836999893188477
    },
    {
        "date": "2025-07-07 15:00:00+00:00",
        "temperature_2m": 17.636999130249023
    },
    {
        "date": "2025-07-07 16:00:00+00:00",
        "temperature_2m": 17.48699951171875
    },
    {
        "date": "2025-07-07 17:00:00+00:00",
        "temperature_2m": 17.786998748779297
    },
    {
        "date": "2025-07-07 18:00:00+00:00",
        "temperature_2m": 18.036998748779297
    },
    {
        "date": "2025-07-07 19:00:00+00:00",
        "temperature_2m": 18.23699951171875
    },
    {
        "date": "2025-07-07 20:00:00+00:00",
        "temperature_2m": 17.73699951171875
    },
    {
        "date": "2025-07-07 21:00:00+00:00",
        "temperature_2m": 16.836999893188477
    },
    {
        "date": "2025-07-07 22:00:00+00:00",
        "temperature_2m": 16.086999893188477
    },
    {
        "date": "2025-07-07 23:00:00+00:00",
        "temperature_2m": 15.53700065612793
    },
    {
        "date": "2025-07-08 00:00:00+00:00",
        "temperature_2m": 15.187000274658203
    },
    {
        "date": "2025-07-08 01:00:00+00:00",
        "temperature_2m": 15.087000846862793
    },
    {
        "date": "2025-07-08 02:00:00+00:00",
        "temperature_2m": 14.687000274658203
    },
    {
        "date": "2025-07-08 03:00:00+00:00",
        "temperature_2m": 14.087000846862793
    },
    {
        "date": "2025-07-08 04:00:00+00:00",
        "temperature_2m": 13.837000846862793
    },
    {
        "date": "2025-07-08 05:00:00+00:00",
        "temperature_2m": 13.78700065612793
    },
    {
        "date": "2025-07-08 06:00:00+00:00",
        "temperature_2m": 14.237000465393066
    },
    {
        "date": "2025-07-08 07:00:00+00:00",
        "temperature_2m": 15.437000274658203
    },
    {
        "date": "2025-07-08 08:00:00+00:00",
        "temperature_2m": 16.636999130249023
    },
    {
        "date": "2025-07-08 09:00:00+00:00",
        "temperature_2m": 17.687000274658203
    },
    {
        "date": "2025-07-08 10:00:00+00:00",
        "temperature_2m": 18.836999893188477
    },
    {
        "date": "2025-07-08 11:00:00+00:00",
        "temperature_2m": 19.687000274658203
    },
    {
        "date": "2025-07-08 12:00:00+00:00",
        "temperature_2m": 20.336999893188477
    },
    {
        "date": "2025-07-08 13:00:00+00:00",
        "temperature_2m": 21.437000274658203
    },
    {
        "date": "2025-07-08 14:00:00+00:00",
        "temperature_2m": 21.536998748779297
    },
    {
        "date": "2025-07-08 15:00:00+00:00",
        "temperature_2m": 22.036998748779297
    },
    {
        "date": "2025-07-08 16:00:00+00:00",
        "temperature_2m": 22.48699951171875
    },
    {
        "date": "2025-07-08 17:00:00+00:00",
        "temperature_2m": 22.086999893188477
    },
    {
        "date": "2025-07-08 18:00:00+00:00",
        "temperature_2m": 21.636999130249023
    },
    {
        "date": "2025-07-08 19:00:00+00:00",
        "temperature_2m": 18.934499740600586
    },
    {
        "date": "2025-07-08 20:00:00+00:00",
        "temperature_2m": 17.384498596191406
    },
    {
        "date": "2025-07-08 21:00:00+00:00",
        "temperature_2m": 16.234498977661133
    },
    {
        "date": "2025-07-08 22:00:00+00:00",
        "temperature_2m": 15.284500122070312
    },
    {
        "date": "2025-07-08 23:00:00+00:00",
        "temperature_2m": 14.534500122070312
    },
    {
        "date": "2025-07-09 00:00:00+00:00",
        "temperature_2m": 13.934500694274902
    },
    {
        "date": "2025-07-09 01:00:00+00:00",
        "temperature_2m": 13.334500312805176
    },
    {
        "date": "2025-07-09 02:00:00+00:00",
        "temperature_2m": 12.834500312805176
    },
    {
        "date": "2025-07-09 03:00:00+00:00",
        "temperature_2m": 12.284500122070312
    },
    {
        "date": "2025-07-09 04:00:00+00:00",
        "temperature_2m": 11.884500503540039
    },
    {
        "date": "2025-07-09 05:00:00+00:00",
        "temperature_2m": 11.934500694274902
    },
    {
        "date": "2025-07-09 06:00:00+00:00",
        "temperature_2m": 13.434500694274902
    },
    {
        "date": "2025-07-09 07:00:00+00:00",
        "temperature_2m": 15.73449993133545
    },
    {
        "date": "2025-07-09 08:00:00+00:00",
        "temperature_2m": 17.934499740600586
    },
    {
        "date": "2025-07-09 09:00:00+00:00",
        "temperature_2m": 19.784500122070312
    },
    {
        "date": "2025-07-09 10:00:00+00:00",
        "temperature_2m": 21.33449935913086
    },
    {
        "date": "2025-07-09 11:00:00+00:00",
        "temperature_2m": 22.534500122070312
    },
    {
        "date": "2025-07-09 12:00:00+00:00",
        "temperature_2m": 23.33449935913086
    },
    {
        "date": "2025-07-09 13:00:00+00:00",
        "temperature_2m": 23.884498596191406
    },
    {
        "date": "2025-07-09 14:00:00+00:00",
        "temperature_2m": 24.134498596191406
    },
    {
        "date": "2025-07-09 15:00:00+00:00",
        "temperature_2m": 24.33449935913086
    },
    {
        "date": "2025-07-09 16:00:00+00:00",
        "temperature_2m": 23.884498596191406
    },
    {
        "date": "2025-07-09 17:00:00+00:00",
        "temperature_2m": 23.33449935913086
    },
    {
        "date": "2025-07-09 18:00:00+00:00",
        "temperature_2m": 23.08449935913086
    },
    {
        "date": "2025-07-09 19:00:00+00:00",
        "temperature_2m": 21.934499740600586
    },
    {
        "date": "2025-07-09 20:00:00+00:00",
        "temperature_2m": 20.484498977661133
    },
    {
        "date": "2025-07-09 21:00:00+00:00",
        "temperature_2m": 19.184499740600586
    },
    {
        "date": "2025-07-09 22:00:00+00:00",
        "temperature_2m": 18.234498977661133
    },
    {
        "date": "2025-07-09 23:00:00+00:00",
        "temperature_2m": 17.484498977661133
    },
    {
        "date": "2025-07-10 00:00:00+00:00",
        "temperature_2m": 16.784500122070312
    },
    {
        "date": "2025-07-10 01:00:00+00:00",
        "temperature_2m": 16.08449935913086
    },
    {
        "date": "2025-07-10 02:00:00+00:00",
        "temperature_2m": 15.48449993133545
    },
    {
        "date": "2025-07-10 03:00:00+00:00",
        "temperature_2m": 15.134500503540039
    },
    {
        "date": "2025-07-10 04:00:00+00:00",
        "temperature_2m": 15.034500122070312
    },
    {
        "date": "2025-07-10 05:00:00+00:00",
        "temperature_2m": 15.134500503540039
    },
    {
        "date": "2025-07-10 06:00:00+00:00",
        "temperature_2m": 15.884500503540039
    },
    {
        "date": "2025-07-10 07:00:00+00:00",
        "temperature_2m": 17.634498596191406
    },
    {
        "date": "2025-07-10 08:00:00+00:00",
        "temperature_2m": 19.934499740600586
    },
    {
        "date": "2025-07-10 09:00:00+00:00",
        "temperature_2m": 21.934499740600586
    },
    {
        "date": "2025-07-10 10:00:00+00:00",
        "temperature_2m": 23.33449935913086
    },
    {
        "date": "2025-07-10 11:00:00+00:00",
        "temperature_2m": 24.434499740600586
    },
    {
        "date": "2025-07-10 12:00:00+00:00",
        "temperature_2m": 25.234498977661133
    },
    {
        "date": "2025-07-10 13:00:00+00:00",
        "temperature_2m": 25.734498977661133
    },
    {
        "date": "2025-07-10 14:00:00+00:00",
        "temperature_2m": 25.934499740600586
    },
    {
        "date": "2025-07-10 15:00:00+00:00",
        "temperature_2m": 25.884498596191406
    },
    {
        "date": "2025-07-10 16:00:00+00:00",
        "temperature_2m": 25.684499740600586
    },
    {
        "date": "2025-07-10 17:00:00+00:00",
        "temperature_2m": 25.234498977661133
    },
    {
        "date": "2025-07-10 18:00:00+00:00",
        "temperature_2m": 24.484498977661133
    },
    {
        "date": "2025-07-10 19:00:00+00:00",
        "temperature_2m": 23.284500122070312
    },
    {
        "date": "2025-07-10 20:00:00+00:00",
        "temperature_2m": 21.784500122070312
    },
    {
        "date": "2025-07-10 21:00:00+00:00",
        "temperature_2m": 20.484498977661133
    },
    {
        "date": "2025-07-10 22:00:00+00:00",
        "temperature_2m": 19.534500122070312
    },
    {
        "date": "2025-07-10 23:00:00+00:00",
        "temperature_2m": 18.784500122070312
    },
    {
        "date": "2025-07-11 00:00:00+00:00",
        "temperature_2m": 18.134498596191406
    },
    {
        "date": "2025-07-11 01:00:00+00:00",
        "temperature_2m": 17.434499740600586
    },
    {
        "date": "2025-07-11 02:00:00+00:00",
        "temperature_2m": 16.784500122070312
    },
    {
        "date": "2025-07-11 03:00:00+00:00",
        "temperature_2m": 16.434499740600586
    },
    {
        "date": "2025-07-11 04:00:00+00:00",
        "temperature_2m": 16.434499740600586
    },
    {
        "date": "2025-07-11 05:00:00+00:00",
        "temperature_2m": 16.684499740600586
    },
    {
        "date": "2025-07-11 06:00:00+00:00",
        "temperature_2m": 17.484498977661133
    },
    {
        "date": "2025-07-11 07:00:00+00:00",
        "temperature_2m": 19.08449935913086
    },
    {
        "date": "2025-07-11 08:00:00+00:00",
        "temperature_2m": 21.234498977661133
    },
    {
        "date": "2025-07-11 09:00:00+00:00",
        "temperature_2m": 23.08449935913086
    },
    {
        "date": "2025-07-11 10:00:00+00:00",
        "temperature_2m": 24.434499740600586
    },
    {
        "date": "2025-07-11 11:00:00+00:00",
        "temperature_2m": 25.534500122070312
    },
    {
        "date": "2025-07-11 12:00:00+00:00",
        "temperature_2m": 26.284500122070312
    },
    {
        "date": "2025-07-11 13:00:00+00:00",
        "temperature_2m": 26.784500122070312
    },
    {
        "date": "2025-07-11 14:00:00+00:00",
        "temperature_2m": 27.184499740600586
    },
    {
        "date": "2025-07-11 15:00:00+00:00",
        "temperature_2m": 27.33449935913086
    },
    {
        "date": "2025-07-11 16:00:00+00:00",
        "temperature_2m": 27.234498977661133
    },
    {
        "date": "2025-07-11 17:00:00+00:00",
        "temperature_2m": 26.83449935913086
    },
    {
        "date": "2025-07-11 18:00:00+00:00",
        "temperature_2m": 26.034500122070312
    },
    {
        "date": "2025-07-11 19:00:00+00:00",
        "temperature_2m": 24.634498596191406
    },
    {
        "date": "2025-07-11 20:00:00+00:00",
        "temperature_2m": 22.884498596191406
    },
    {
        "date": "2025-07-11 21:00:00+00:00",
        "temperature_2m": 21.33449935913086
    },
    {
        "date": "2025-07-11 22:00:00+00:00",
        "temperature_2m": 20.234498977661133
    },
    {
        "date": "2025-07-11 23:00:00+00:00",
        "temperature_2m": 19.384498596191406
    },
    {
        "date": "2025-07-12 00:00:00+00:00",
        "temperature_2m": 18.58449935913086
    },
    {
        "date": "2025-07-12 01:00:00+00:00",
        "temperature_2m": 17.784500122070312
    },
    {
        "date": "2025-07-12 02:00:00+00:00",
        "temperature_2m": 17.08449935913086
    },
    {
        "date": "2025-07-12 03:00:00+00:00",
        "temperature_2m": 16.734498977661133
    },
    {
        "date": "2025-07-12 04:00:00+00:00",
        "temperature_2m": 16.784500122070312
    },
    {
        "date": "2025-07-12 05:00:00+00:00",
        "temperature_2m": 17.184499740600586
    },
    {
        "date": "2025-07-12 06:00:00+00:00",
        "temperature_2m": 17.984498977661133
    },
    {
        "date": "2025-07-12 07:00:00+00:00",
        "temperature_2m": 19.434499740600586
    },
    {
        "date": "2025-07-12 08:00:00+00:00",
        "temperature_2m": 21.33449935913086
    },
    {
        "date": "2025-07-12 09:00:00+00:00",
        "temperature_2m": 23.08449935913086
    },
    {
        "date": "2025-07-12 10:00:00+00:00",
        "temperature_2m": 24.534500122070312
    },
    {
        "date": "2025-07-12 11:00:00+00:00",
        "temperature_2m": 25.784500122070312
    },
    {
        "date": "2025-07-12 12:00:00+00:00",
        "temperature_2m": 26.784500122070312
    },
    {
        "date": "2025-07-12 13:00:00+00:00",
        "temperature_2m": 27.434499740600586
    },
    {
        "date": "2025-07-12 14:00:00+00:00",
        "temperature_2m": 27.784500122070312
    },
    {
        "date": "2025-07-12 15:00:00+00:00",
        "temperature_2m": 27.934499740600586
    },
    {
        "date": "2025-07-12 16:00:00+00:00",
        "temperature_2m": 27.984498977661133
    },
    {
        "date": "2025-07-12 17:00:00+00:00",
        "temperature_2m": 27.83449935913086
    },
    {
        "date": "2025-07-12 18:00:00+00:00",
        "temperature_2m": 27.184499740600586
    },
    {
        "date": "2025-07-12 19:00:00+00:00",
        "temperature_2m": 25.684499740600586
    },
    {
        "date": "2025-07-12 20:00:00+00:00",
        "temperature_2m": 23.684499740600586
    },
    {
        "date": "2025-07-12 21:00:00+00:00",
        "temperature_2m": 21.934499740600586
    },
    {
        "date": "2025-07-12 22:00:00+00:00",
        "temperature_2m": 20.83449935913086
    },
    {
        "date": "2025-07-12 23:00:00+00:00",
        "temperature_2m": 19.984498977661133
    }
]